sphinx_markdown_builder/__init__.py
sphinx_markdown_builder/depth.py
sphinx_markdown_builder/doctree2md.py
sphinx_markdown_builder/markdown_builder.py
sphinx_markdown_builder/markdown_writer.py
sphinxnotes_markdown_builder-0.5.7.dist-info/LICENSE
sphinxnotes_markdown_builder-0.5.7.dist-info/METADATA
sphinxnotes_markdown_builder-0.5.7.dist-info/WHEEL
sphinxnotes_markdown_builder-0.5.7.dist-info/entry_points.txt
sphinxnotes_markdown_builder-0.5.7.dist-info/top_level.txt
sphinxnotes_markdown_builder-0.5.7.dist-info/RECORD
