Metadata-Version: 2.1
Name: sphinxnotes-markdown-builder
Version: 0.5.7
Summary: sphinx builder that outputs markdown files, an active fork of clayrisser/sphinx-markdown-builder
Home-page: https://github.com/sphinx-notes/markdown-builder
Author: Shengyu Zhang
Author-email: jam@codejam.ninja
License: MIT
Keywords: sphinx docs documentation markdown
Classifier: Development Status :: 7 - Inactive
Classifier: Intended Audience :: Developers
Classifier: Topic :: Utilities
Classifier: License :: OSI Approved :: MIT License
Classifier: Programming Language :: Python :: 2
Classifier: Programming Language :: Python :: 2.7
Classifier: Programming Language :: Python :: 3
Classifier: Programming Language :: Python :: 3.5
Classifier: Programming Language :: Python :: 3.6
Classifier: Programming Language :: Python :: 3.7
License-File: LICENSE
Requires-Dist: html2text
Requires-Dist: pydash
Requires-Dist: sphinx
Requires-Dist: unify
Requires-Dist: yapf
